pyvarint/__init__.py
pyvarint/varint.py
pyvarint-0.0.1a2.dist-info/LICENSE
pyvarint-0.0.1a2.dist-info/WHEEL
pyvarint-0.0.1a2.dist-info/METADATA
pyvarint-0.0.1a2.dist-info/RECORD
